{
  "train_path": "../imagenet-stuff/train.lmdb",
  "val_path": "../imagenet-stuff/val.lmdb",
  "optimizers": {
    "sgd": {
      "base_lr": 0.01,
      "momentum": 0.9,
      "weight_decay": 0
    },
    "adam": {
      "base_lr": 0.002,
      "weight_decay": 0
    }
  },
  "chosen_optimizer": "adam",
  "scheduler_update_list": [30, 60, 90, 120, 150, 180, 210, 240],
  "max_epoch": 250,
  "batch_size": 256,
  "num_classes": 1000,
  "debug": false,
  "resume": false,
  "use_binary": true,
  "use_bireal_binactive": true,
  "num_workers": 32
}
